{
    "data": {
        "attributes": {
            "categories": {},
            "creation_date": 1556281402,
            "last_analysis_results": {
                "ADMINUSLabs": {
                    "category": "harmless",
                    "engine_name": "ADMINUSLabs",
                    "method": "blacklist",
                    "result": "clean"
                },
                "AegisLab WebGuard": {
                    "category": "harmless",
                    "engine_name": "AegisLab WebGuard",
                    "method": "blacklist",
                    "result": "clean"
                },
                "AlienVault": {
                    "category": "harmless",
                    "engine_name": "AlienVault",
                    "method": "blacklist",
                    "result": "clean"
                },
                "Antiy-AVL": {
                    "category": "harmless",
                    "engine_name": "Antiy-AVL",
                    "method": "blacklist",
                    "result": "clean"
                },
                "Artists Against 419": {
                    "category": "harmless",
                    "engine_name": "Artists Against 419",
                    "method": "blacklist",
                    "result": "clean"
                },
                "AutoShun": {
                    "category": "undetected",
                    "engine_name": "AutoShun",
                    "method": "blacklist",
                    "result": "unrated"
                },
                "Avira": {
                    "category": "harmless",
                    "engine_name": "Avira",
                    "method": "blacklist",
                    "result": "clean"
                },
                "BADWARE.INFO": {
                    "category": "harmless",
                    "engine_name": "BADWARE.INFO",
                    "method": "blacklist",
                    "result": "clean"
                },
                "Baidu-International": {
                    "category": "harmless",
                    "engine_name": "Baidu-International",
                    "method": "blacklist",
                    "result": "clean"
                },
                "BitDefender": {
                    "category": "harmless",
                    "engine_name": "BitDefender",
                    "method": "blacklist",
                    "result": "clean"
                },
                "BlockList": {
                    "category": "harmless",
                    "engine_name": "BlockList",
                    "method": "blacklist",
                    "result": "clean"
                },
                "Blueliv": {
                    "category": "harmless",
                    "engine_name": "Blueliv",
                    "method": "blacklist",
                    "result": "clean"
                },
                "Botvrij.eu": {
                    "category": "harmless",
                    "engine_name": "Botvrij.eu",
                    "method": "blacklist",
                    "result": "clean"
                },
                "CINS Army": {
                    "category": "harmless",
                    "engine_name": "CINS Army",
                    "method": "blacklist",
                    "result": "clean"
                },
                "CLEAN MX": {
                    "category": "harmless",
                    "engine_name": "CLEAN MX",
                    "method": "blacklist",
                    "result": "clean"
                },
                "CRDF": {
                    "category": "harmless",
                    "engine_name": "CRDF",
                    "method": "blacklist",
                    "result": "clean"
                },
                "Certego": {
                    "category": "harmless",
                    "engine_name": "Certego",
                    "method": "blacklist",
                    "result": "clean"
                },
                "Comodo Valkyrie Verdict": {
                    "category": "harmless",
                    "engine_name": "Comodo Valkyrie Verdict",
                    "method": "blacklist",
                    "result": "clean"
                },
                "CyRadar": {
                    "category": "harmless",
                    "engine_name": "CyRadar",
                    "method": "blacklist",
                    "result": "clean"
                },
                "Cyan": {
                    "category": "undetected",
                    "engine_name": "Cyan",
                    "method": "blacklist",
                    "result": "unrated"
                },
                "CyberCrime": {
                    "category": "harmless",
                    "engine_name": "CyberCrime",
                    "method": "blacklist",
                    "result": "clean"
                },
                "Cyren": {
                    "category": "harmless",
                    "engine_name": "Cyren",
                    "method": "blacklist",
                    "result": "clean"
                },
                "DNS8": {
                    "category": "harmless",
                    "engine_name": "DNS8",
                    "method": "blacklist",
                    "result": "clean"
                },
                "Dr.Web": {
                    "category": "harmless",
                    "engine_name": "Dr.Web",
                    "method": "blacklist",
                    "result": "clean"
                },
                "ESET": {
                    "category": "harmless",
                    "engine_name": "ESET",
                    "method": "blacklist",
                    "result": "clean"
                },
                "ESTsecurity-Threat Inside": {
                    "category": "harmless",
                    "engine_name": "ESTsecurity-Threat Inside",
                    "method": "blacklist",
                    "result": "clean"
                },
                "EmergingThreats": {
                    "category": "harmless",
                    "engine_name": "EmergingThreats",
                    "method": "blacklist",
                    "result": "clean"
                },
                "Emsisoft": {
                    "category": "harmless",
                    "engine_name": "Emsisoft",
                    "method": "blacklist",
                    "result": "clean"
                },
                "EonScope": {
                    "category": "harmless",
                    "engine_name": "EonScope",
                    "method": "blacklist",
                    "result": "clean"
                },
                "Feodo Tracker": {
                    "category": "harmless",
                    "engine_name": "Feodo Tracker",
                    "method": "blacklist",
                    "result": "clean"
                },
                "Forcepoint ThreatSeeker": {
                    "category": "harmless",
                    "engine_name": "Forcepoint ThreatSeeker",
                    "method": "blacklist",
                    "result": "clean"
                },
                "Fortinet": {
                    "category": "harmless",
                    "engine_name": "Fortinet",
                    "method": "blacklist",
                    "result": "clean"
                },
                "FraudScore": {
                    "category": "harmless",
                    "engine_name": "FraudScore",
                    "method": "blacklist",
                    "result": "clean"
                },
                "G-Data": {
                    "category": "harmless",
                    "engine_name": "G-Data",
                    "method": "blacklist",
                    "result": "clean"
                },
                "Google Safebrowsing": {
                    "category": "harmless",
                    "engine_name": "Google Safebrowsing",
                    "method": "blacklist",
                    "result": "clean"
                },
                "GreenSnow": {
                    "category": "harmless",
                    "engine_name": "GreenSnow",
                    "method": "blacklist",
                    "result": "clean"
                },
                "Hoplite Industries": {
                    "category": "harmless",
                    "engine_name": "Hoplite Industries",
                    "method": "blacklist",
                    "result": "clean"
                },
                "IPsum": {
                    "category": "harmless",
                    "engine_name": "IPsum",
                    "method": "blacklist",
                    "result": "clean"
                },
                "K7AntiVirus": {
                    "category": "harmless",
                    "engine_name": "K7AntiVirus",
                    "method": "blacklist",
                    "result": "clean"
                },
                "Kaspersky": {
                    "category": "harmless",
                    "engine_name": "Kaspersky",
                    "method": "blacklist",
                    "result": "clean"
                },
                "Lumu": {
                    "category": "undetected",
                    "engine_name": "Lumu",
                    "method": "blacklist",
                    "result": "unrated"
                },
                "MalBeacon": {
                    "category": "harmless",
                    "engine_name": "MalBeacon",
                    "method": "blacklist",
                    "result": "clean"
                },
                "MalSilo": {
                    "category": "harmless",
                    "engine_name": "MalSilo",
                    "method": "blacklist",
                    "result": "clean"
                },
                "Malware Domain Blocklist": {
                    "category": "harmless",
                    "engine_name": "Malware Domain Blocklist",
                    "method": "blacklist",
                    "result": "clean"
                },
                "MalwareDomainList": {
                    "category": "harmless",
                    "engine_name": "MalwareDomainList",
                    "method": "blacklist",
                    "result": "clean"
                },
                "MalwarePatrol": {
                    "category": "harmless",
                    "engine_name": "MalwarePatrol",
                    "method": "blacklist",
                    "result": "clean"
                },
                "Malwarebytes hpHosts": {
                    "category": "harmless",
                    "engine_name": "Malwarebytes hpHosts",
                    "method": "blacklist",
                    "result": "clean"
                },
                "Malwared": {
                    "category": "harmless",
                    "engine_name": "Malwared",
                    "method": "blacklist",
                    "result": "clean"
                },
                "Netcraft": {
                    "category": "harmless",
                    "engine_name": "Netcraft",
                    "method": "blacklist",
                    "result": "clean"
                },
                "NotMining": {
                    "category": "undetected",
                    "engine_name": "NotMining",
                    "method": "blacklist",
                    "result": "unrated"
                },
                "Nucleon": {
                    "category": "harmless",
                    "engine_name": "Nucleon",
                    "method": "blacklist",
                    "result": "clean"
                },
                "OpenPhish": {
                    "category": "harmless",
                    "engine_name": "OpenPhish",
                    "method": "blacklist",
                    "result": "clean"
                },
                "PREBYTES": {
                    "category": "harmless",
                    "engine_name": "PREBYTES",
                    "method": "blacklist",
                    "result": "clean"
                },
                "PhishLabs": {
                    "category": "undetected",
                    "engine_name": "PhishLabs",
                    "method": "blacklist",
                    "result": "unrated"
                },
                "Phishing Database": {
                    "category": "harmless",
                    "engine_name": "Phishing Database",
                    "method": "blacklist",
                    "result": "clean"
                },
                "Phishtank": {
                    "category": "harmless",
                    "engine_name": "Phishtank",
                    "method": "blacklist",
                    "result": "clean"
                },
                "Quick Heal": {
                    "category": "harmless",
                    "engine_name": "Quick Heal",
                    "method": "blacklist",
                    "result": "clean"
                },
                "Quttera": {
                    "category": "harmless",
                    "engine_name": "Quttera",
                    "method": "blacklist",
                    "result": "clean"
                },
                "Rising": {
                    "category": "harmless",
                    "engine_name": "Rising",
                    "method": "blacklist",
                    "result": "clean"
                },
                "SCUMWARE.org": {
                    "category": "harmless",
                    "engine_name": "SCUMWARE.org",
                    "method": "blacklist",
                    "result": "clean"
                },
                "Sangfor": {
                    "category": "harmless",
                    "engine_name": "Sangfor",
                    "method": "blacklist",
                    "result": "clean"
                },
                "SecureBrain": {
                    "category": "harmless",
                    "engine_name": "SecureBrain",
                    "method": "blacklist",
                    "result": "clean"
                },
                "Segasec": {
                    "category": "harmless",
                    "engine_name": "Segasec",
                    "method": "blacklist",
                    "result": "clean"
                },
                "Snort IP sample list": {
                    "category": "harmless",
                    "engine_name": "Snort IP sample list",
                    "method": "blacklist",
                    "result": "clean"
                },
                "Sophos": {
                    "category": "harmless",
                    "engine_name": "Sophos",
                    "method": "blacklist",
                    "result": "clean"
                },
                "Spam404": {
                    "category": "harmless",
                    "engine_name": "Spam404",
                    "method": "blacklist",
                    "result": "clean"
                },
                "Spamhaus": {
                    "category": "harmless",
                    "engine_name": "Spamhaus",
                    "method": "blacklist",
                    "result": "clean"
                },
                "StopBadware": {
                    "category": "undetected",
                    "engine_name": "StopBadware",
                    "method": "blacklist",
                    "result": "unrated"
                },
                "StopForumSpam": {
                    "category": "harmless",
                    "engine_name": "StopForumSpam",
                    "method": "blacklist",
                    "result": "clean"
                },
                "Sucuri SiteCheck": {
                    "category": "harmless",
                    "engine_name": "Sucuri SiteCheck",
                    "method": "blacklist",
                    "result": "clean"
                },
                "Tencent": {
                    "category": "harmless",
                    "engine_name": "Tencent",
                    "method": "blacklist",
                    "result": "clean"
                },
                "ThreatHive": {
                    "category": "harmless",
                    "engine_name": "ThreatHive",
                    "method": "blacklist",
                    "result": "clean"
                },
                "Threatsourcing": {
                    "category": "harmless",
                    "engine_name": "Threatsourcing",
                    "method": "blacklist",
                    "result": "clean"
                },
                "Trustwave": {
                    "category": "undetected",
                    "engine_name": "Trustwave",
                    "method": "blacklist",
                    "result": "unrated"
                },
                "URLhaus": {
                    "category": "harmless",
                    "engine_name": "URLhaus",
                    "method": "blacklist",
                    "result": "clean"
                },
                "VX Vault": {
                    "category": "harmless",
                    "engine_name": "VX Vault",
                    "method": "blacklist",
                    "result": "clean"
                },
                "Virusdie External Site Scan": {
                    "category": "harmless",
                    "engine_name": "Virusdie External Site Scan",
                    "method": "blacklist",
                    "result": "clean"
                },
                "Web Security Guard": {
                    "category": "harmless",
                    "engine_name": "Web Security Guard",
                    "method": "blacklist",
                    "result": "clean"
                },
                "Yandex Safebrowsing": {
                    "category": "harmless",
                    "engine_name": "Yandex Safebrowsing",
                    "method": "blacklist",
                    "result": "clean"
                },
                "ZeroCERT": {
                    "category": "harmless",
                    "engine_name": "ZeroCERT",
                    "method": "blacklist",
                    "result": "clean"
                },
                "desenmascara.me": {
                    "category": "harmless",
                    "engine_name": "desenmascara.me",
                    "method": "blacklist",
                    "result": "clean"
                },
                "malwares.com URL checker": {
                    "category": "harmless",
                    "engine_name": "malwares.com URL checker",
                    "method": "blacklist",
                    "result": "clean"
                },
                "securolytics": {
                    "category": "harmless",
                    "engine_name": "securolytics",
                    "method": "blacklist",
                    "result": "clean"
                },
                "zvelo": {
                    "category": "harmless",
                    "engine_name": "zvelo",
                    "method": "blacklist",
                    "result": "clean"
                }
            },
            "last_analysis_stats": {
                "harmless": 78,
                "malicious": 0,
                "suspicious": 0,
                "timeout": 0,
                "undetected": 7
            },
            "last_dns_records": [
                {
                    "expire": 1209600,
                    "minimum": 3600,
                    "refresh": 7200,
                    "retry": 1800,
                    "rname": "support.cloudns.net",
                    "serial": 2020092805,
                    "ttl": 3599,
                    "type": "SOA",
                    "value": "ns1.perfectdns.com"
                },
                {
                    "ttl": 3599,
                    "type": "NS",
                    "value": "ns1.perfectdns.com"
                },
                {
                    "ttl": 1799,
                    "type": "A",
                    "value": "188.165.29.223"
                },
                {
                    "ttl": 3599,
                    "type": "NS",
                    "value": "ns2.perfectdns.com"
                }
            ],
            "last_dns_records_date": 1601330586,
            "last_https_certificate": {
                "cert_signature": {
                    "signature": "0a0dc2af490bb92962cf7f9ce9cc73fec6d6965c3522f96ac34506037df69453cb6c61211fada786bf20c4cce354a13b3d34fd4e47fcd55cc3fed627a78f3dbc8c32473c35d3cc76f7043b35052c64bf64bf493887201d94b1182411737912db8e401859e476eb50e90ec28d6b4c0cf136bc729ce00af4b2a3e1be90e88bb1395e38a8b6d292c9e0009e3f836d5b1116fbaf4048753b19cab6e285ed549e608f01a68773b357ab08288dd79417adc87d7c52132be207acc13477f3002ecdcadc527546cd6ef63b1cb44f225fe6c415ca8c5a6b6248baab694e048ae95a1971a954fde4f585c92baa2578aa191c6dd9c345d8db2b90c28cb733b2f16d24a9e7ad",
                    "signature_algorithm": "sha256RSA"
                },
                "extensions": {
                    "1.3.6.1.4.1.11129.2.4.2": "0481f200f0007600f095a459f200d18240102d2f93888ead4bfe1d47e399e1d0",
                    "CA": true,
                    "authority_key_identifier": {
                        "keyid": "a84a6a63047dddbae6d139b7a64565eff3a8eca1"
                    },
                    "ca_information_access": {
                        "CA Issuers": "http://cert.int-x3.letsencrypt.org/",
                        "OCSP": "http://ocsp.int-x3.letsencrypt.org"
                    },
                    "certificate_policies": [
                        "2.23.140.1.2.1",
                        "1.3.6.1.4.1.44947.1.1.1"
                    ],
                    "extended_key_usage": [
                        "serverAuth",
                        "clientAuth"
                    ],
                    "key_usage": [
                        "ff"
                    ],
                    "subject_alternative_name": [
                        "socialworldpanel.com",
                        "www.socialworldpanel.com"
                    ],
                    "subject_key_identifier": "59d5138d8733fd1079209b2d68f87c087237477d",
                    "tags": []
                },
                "issuer": {
                    "C": "US",
                    "CN": "Let's Encrypt Authority X3",
                    "O": "Let's Encrypt"
                },
                "public_key": {
                    "algorithm": "RSA",
                    "rsa": {
                        "exponent": "010001",
                        "key_size": 2048,
                        "modulus": "00ddc398ba97b92cda9091b635e6cc46901796c87d07dc67228c864acf96ae08866c7f6c6a2f7e2b48c00b03723de37cc8bad2d68806fe1a8468d659e7666013f01e622312a1f5afc81c585e94907c0882bd5db8a791d2e37e9fc6a39fe2f38681f48dcaed44b53a78ab795e72b3df129a6d20f1706f3f9f4c7cd35a3e2d552352ca8b2310dcc07bd1bb89cdf54e70a582462af45e27ffaa0bc856bfac6bcafc826f347c835a1f496db53198782218a0b959e55ac85a0645beea1c58d475bf295a1a8405170a48fb8102b0d9c805d34ca3e879b72cb3217ada68d03057920ca1fb092ce0d68cc35fec84f31de4daf6cb0271bb2bd2286642307a5d58df1781d1e1"
                    }
                },
                "serial_number": "3f8e40085a3d4a03bc10d62e849c4c87d0a",
                "signature_algorithm": "sha256RSA",
                "size": 1406,
                "subject": {
                    "CN": "socialworldpanel.com"
                },
                "tags": [],
                "thumbprint": "f8a90ad14a423bcdf322e4b77adf129a57bdf963",
                "thumbprint_sha256": "5735e3b1e4d6a9936746cf6158508bef82809c1f1346701e6ffd9fea998556c0",
                "validity": {
                    "not_after": "2020-12-27 07:43:04",
                    "not_before": "2020-09-28 07:43:04"
                },
                "version": "V3"
            },
            "last_https_certificate_date": 1601330586,
            "last_modification_date": 1602689834,
            "last_update_date": 1600781892,
            "popularity_ranks": {
                "Alexa": {
                    "rank": 145905,
                    "timestamp": 1602689763
                },
                "Statvoo": {
                    "rank": 272565,
                    "timestamp": 1602689766
                }
            },
            "registrar": "GoDaddy.com, LLC",
            "reputation": 0,
            "tags": [],
            "total_votes": {
                "harmless": 0,
                "malicious": 0
            },
            "whois": "Admin City: Scottsdale\nAdmin Country: US\nAdmin Email: 4247eb35ad805688s@domainsbyproxy.com\nAdmin Organization: Domains By Proxy, LLC\nAdmin Postal Code: 85260\nAdmin State/Province: Arizona\nCreation Date: 2019-04-26T12:23:22Z\nDNSSEC: unsigned\nDomain Name: SOCIALWORLDPANEL.COM\nDomain Name: socialworldpanel.com\nDomain Status: clientDeleteProhibited http://www.icann.org/epp#clientDeleteProhibited\nDomain Status: clientDeleteProhibited https://icann.org/epp#clientDeleteProhibited\nDomain Status: clientRenewProhibited http://www.icann.org/epp#clientRenewProhibited\nDomain Status: clientRenewProhibited https://icann.org/epp#clientRenewProhibited\nDomain Status: clientTransferProhibited http://www.icann.org/epp#clientTransferProhibited\nDomain Status: clientTransferProhibited https://icann.org/epp#clientTransferProhibited\nDomain Status: clientUpdateProhibited http://www.icann.org/epp#clientUpdateProhibited\nDomain Status: clientUpdateProhibited https://icann.org/epp#clientUpdateProhibited\nName Server: NS1.PERFECTDNS.COM\nName Server: NS2.PERFECTDNS.COM\nRegistrant City: 373f4980ad3d2d01\nRegistrant Country: US\nRegistrant Email: 4247eb35ad805688s@domainsbyproxy.com\nRegistrant Fax Ext: 3432650ec337c945\nRegistrant Fax: 9fad764be0c7e95d\nRegistrant Name: 80315b2e6ac1a801\nRegistrant Organization: b46a98a26fe2fd9f\nRegistrant Phone Ext: 3432650ec337c945\nRegistrant Phone: d5f66d3a005b000d\nRegistrant Postal Code: b9448b1c75ff534d\nRegistrant State/Province: 30bdd2917a604c83\nRegistrant Street: 037792fd5a6fe619\nRegistrant Street: f38c0adea706dbc3\nRegistrar Abuse Contact Email: abuse@godaddy.com\nRegistrar Abuse Contact Phone: +1.4806242505\nRegistrar Abuse Contact Phone: 480-624-2505\nRegistrar IANA ID: 146\nRegistrar Registration Expiration Date: 2021-04-26T12:23:22Z\nRegistrar URL: http://www.godaddy.com\nRegistrar WHOIS Server: whois.godaddy.com\nRegistrar: GoDaddy.com, LLC\nRegistry Admin ID: Not Available From Registry\nRegistry Domain ID: 2384547107_DOMAIN_COM-VRSN\nRegistry Expiry Date: 2021-04-26T12:23:22Z\nRegistry Registrant ID: Not Available From Registry\nRegistry Tech ID: Not Available From Registry\nTech City: Scottsdale\nTech Country: US\nTech Email: 4247eb35ad805688s@domainsbyproxy.com\nTech Organization: Domains By Proxy, LLC\nTech Postal Code: 85260\nTech State/Province: Arizona\nUpdated Date: 2020-05-11T13:08:33Z\nUpdated Date: 2020-09-22T13:38:12Z",
            "whois_date": 1600916625
        },
        "id": "socialworldpanel.com",
        "links": {
            "self": "https://www.virustotal.com/api/v3/domains/socialworldpanel.com"
        },
        "type": "domain"
    }
}